{
  "type": "Feature",
  "properties": {
    "iso:country":"PL",
    "sg:address":"ul. Bukowska 352",
    "sg:city":"Poznan",
    "sg:classifiers":[
        {
            "category":"Professional",
            "subcategory":"Computer Services",
            "type":"Services"
        }
    ],
    "sg:postcode":"60-189",
    "sg:tags":[
        "linux",
        "server",
        "management"
    ],
    "sg:website":"http://www.xandros.com",
    "wof:name":"Xandros",
    "wof:placetype":"venue"
},
  "geometry": {"coordinates":[16.827764,52.413065],"type":"Point"}
}