{
  "type": "Feature",
  "properties": {
    "iso:country":"PL",
    "sg:address":"Krzemowa 6",
    "sg:city":"Gdynia",
    "sg:classifiers":[
        {
            "category":"Manufacturing",
            "subcategory":"Electronics",
            "type":"Manufacturing & Wholesale Goods"
        }
    ],
    "sg:postcode":"81577",
    "sg:tags":[
        "telecommunication",
        "computing",
        "television",
        "nets",
        "cable-nets",
        "cable-television",
        "hfc-net",
        "data-transmission",
        "ip-telephony",
        "voip",
        "digital-television",
        "vod",
        "video-on-demand",
        "nvod",
        "headends",
        "dwdm",
        "power-supply-systems",
        "an",
        "man",
        "lan",
        "wireless",
        "iptv",
        "cisco",
        "dlink"
    ],
    "sg:website":"http://www.vector.com.pl",
    "wof:name":"VECTOR",
    "wof:placetype":"venue"
},
  "geometry": {"coordinates":[18.455176,54.457973],"type":"Point"}
}